joshq/__init__.py
joshq/joshq.py
joshq/bin/joshq
joshq-0.0.4.data/scripts/joshq
joshq-0.0.4.dist-info/METADATA
joshq-0.0.4.dist-info/WHEEL
joshq-0.0.4.dist-info/top_level.txt
joshq-0.0.4.dist-info/RECORD
